Python_crawler-0.1.0.dist-info/DESCRIPTION.rst
Python_crawler-0.1.0.dist-info/METADATA
Python_crawler-0.1.0.dist-info/RECORD
Python_crawler-0.1.0.dist-info/WHEEL
Python_crawler-0.1.0.dist-info/entry_points.txt
Python_crawler-0.1.0.dist-info/metadata.json
Python_crawler-0.1.0.dist-info/top_level.txt
crawler/__init__.py
crawler/cli.py
crawler/crawler.py
