Metadata-Version: 2.0
Name: Python-crawler
Version: 0.1.0
Summary: Cralwer is a simple 2 site webspider
Home-page: https://github.com/jrightwords/crawler
Author: George Gorbunov
Author-email: jrightwords@yandex.ru
License: GNU General Public License v3
Keywords: crawler
Platform: UNKNOWN
Classifier: Development Status :: 2 - Pre-Alpha
Classifier: Intended Audience :: Developers
Classifier: License :: OSI Approved :: GNU General Public License v3 (GPLv3)
Classifier: Natural Language :: English
Classifier: Programming Language :: Python :: 2
Classifier: Programming Language :: Python :: 2.6
Classifier: Programming Language :: Python :: 2.7
Classifier: Programming Language :: Python :: 3
Classifier: Programming Language :: Python :: 3.3
Classifier: Programming Language :: Python :: 3.4
Classifier: Programming Language :: Python :: 3.5
Requires-Dist: Click (>=6.0)
